{
  "address1": "6-15 Chuo 2-jo 3-chome",
  "address2": "Shiroishi-ku",
  "city": "Sapporo",
  "zip": "003-0012",
  "country": "Japan",
  "phone": "81 11 812 1131",
  "website": "https://www.hokuryo.co.jp",
  "industry": "Farm Products",
  "industryKey": "farm-products",
  "industryDisp": "Farm Products",
  "sector": "Consumer Defensive",
  "sectorKey": "consumer-defensive",
  "sectorDisp": "Consumer Defensive",
  "longBusinessSummary": "Hokuryo Co., Ltd. engages in the production and sale of eggs in Japan. The company was incorporated in 1949 and is headquartered in Sapporo, Japan.",
  "fullTimeEmployees": 235,
  "companyOfficers": [
    {
      "maxAge": 1,
      "name": "Mr. Daisuke  Yoneyama",
      "age": 67,
      "title": "President, CEO & Representative Director",
      "yearBorn": 1958,
      "exercisedValue": 0,
      "unexercisedValue": 0
    },
    {
      "maxAge": 1,
      "name": "Mr. Shin  Sato",
      "title": "Executive Officer & GM of Accounting Department",
      "exercisedValue": 0,
      "unexercisedValue": 0
    },
    {
      "maxAge": 1,
      "name": "Mr. Naoki  Fukushima",
      "age": 65,
      "title": "MD, GM of Sales Division & Director",
      "yearBorn": 1960,
      "exercisedValue": 0,
      "unexercisedValue": 0
    },
    {
      "maxAge": 1,
      "name": "Mr. Yasuhiro  Kudo",
      "age": 70,
      "title": "Chairman of Audit & Supervisory Board Members",
      "yearBorn": 1955,
      "exercisedValue": 0,
      "unexercisedValue": 0
    },
    {
      "maxAge": 1,
      "name": "Mr. Shintaro  Matsuno",
      "title": "Executive Officer & GM of Production Headquarters",
      "exercisedValue": 0,
      "unexercisedValue": 0
    },
    {
      "maxAge": 1,
      "name": "Mr. Masaya  Matsuoka",
      "age": 66,
      "title": "Senior MD, Head of Planning Division & Director",
      "yearBorn": 1959,
      "exercisedValue": 0,
      "unexercisedValue": 0
    },
    {
      "maxAge": 1,
      "name": "Mr. Masayuki  Aida",
      "title": "Executive Officer & GM of General Affairs Department",
      "exercisedValue": 0,
      "unexercisedValue": 0
    },
    {
      "maxAge": 1,
      "name": "Mr. Hiroyuki  Maeda",
      "title": "Executive Officer & GM of Manufacturing Headquarters",
      "exercisedValue": 0,
      "unexercisedValue": 0
    },
    {
      "maxAge": 1,
      "name": "Seiji  Yamakado",
      "age": 61,
      "title": "Head of Management Headquarters & Director",
      "yearBorn": 1964,
      "exercisedValue": 0,
      "unexercisedValue": 0
    }
  ],
  "executiveTeam": [],
  "maxAge": 86400,
  "priceHint": 2,
  "previousClose": 3200.0,
  "open": 3160.0,
  "dayLow": 3070.0,
  "dayHigh": 3185.0,
  "regularMarketPreviousClose": 3200.0,
  "regularMarketOpen": 3160.0,
  "regularMarketDayLow": 3070.0,
  "regularMarketDayHigh": 3185.0,
  "dividendRate": 120.0,
  "dividendYield": 3.9,
  "exDividendDate": 1774828800,
  "payoutRatio": 0.20030001,
  "fiveYearAvgDividendYield": 2.75,
  "beta": 0.37,
  "trailingPE": 8.810573,
  "volume": 47500,
  "regularMarketVolume": 47500,
  "averageVolume": 52225,
  "averageVolume10days": 93120,
  "averageDailyVolume10Day": 93120,
  "bid": 3070.0,
  "ask": 3085.0,
  "bidSize": 0,
  "askSize": 0,
  "marketCap": 26053357568,
  "fiftyTwoWeekLow": 1215.0,
  "fiftyTwoWeekHigh": 3385.0,
  "allTimeHigh": 3385.0,
  "allTimeLow": 473.0,
  "priceToSalesTrailing12Months": 1.7748728,
  "fiftyDayAverage": 3047.04,
  "twoHundredDayAverage": 2339.78,
  "trailingAnnualDividendRate": 10.0,
  "trailingAnnualDividendYield": 0.003125,
  "currency": "JPY",
  "tradeable": false,
  "enterpriseValue": 26627571712,
  "profitMargins": 0.07208,
  "floatShares": 3985604,
  "sharesOutstanding": 8458882,
  "heldPercentInsiders": 0.53751,
  "heldPercentInstitutions": 0.06531,
  "impliedSharesOutstanding": 8458882,
  "bookValue": 1170.476,
  "priceToBook": 2.6314082,
  "lastFiscalYearEnd": 1617148800,
  "nextFiscalYearEnd": 1648684800,
  "mostRecentQuarter": 1632960000,
  "netIncomeToCommon": 1058000000,
  "trailingEps": 349.58,
  "enterpriseToRevenue": 1.814,
  "enterpriseToEbitda": 10.815,
  "52WeekChange": 1.1828489,
  "SandP52WeekChange": 0.15480888,
  "lastDividendValue": 120.0,
  "lastDividendDate": 1774828800,
  "quoteType": "EQUITY",
  "currentPrice": 3080.0,
  "recommendationKey": "none",
  "totalCash": 2495000064,
  "totalCashPerShare": 294.954,
  "ebitda": 2462000128,
  "totalDebt": 3068999936,
  "quickRatio": 0.969,
  "currentRatio": 1.183,
  "totalRevenue": 14679000064,
  "debtToEquity": 30.997,
  "revenuePerShare": 1735.321,
  "returnOnAssets": 0.05743,
  "returnOnEquity": 0.11241999,
  "grossProfits": 3371000064,
  "freeCashflow": 1047374976,
  "operatingCashflow": 1944000000,
  "revenueGrowth": 0.304,
  "grossMargins": 0.22965,
  "ebitdaMargins": 0.16771999,
  "operatingMargins": 0.14823,
  "financialCurrency": "JPY",
  "symbol": "1384.T",
  "language": "en-US",
  "region": "US",
  "typeDisp": "Equity",
  "quoteSourceName": "Delayed Quote",
  "triggerable": false,
  "customPriceAlertConfidence": "LOW",
  "regularMarketChangePercent": -3.7500002,
  "regularMarketPrice": 3080.0,
  "marketState": "CLOSED",
  "hasPrePostMarketData": false,
  "firstTradeDateMilliseconds": 1424390400000,
  "regularMarketChange": -120.0,
  "regularMarketDayRange": "3070.0 - 3185.0",
  "fullExchangeName": "Tokyo",
  "averageDailyVolume3Month": 52225,
  "fiftyTwoWeekLowChange": 1865.0,
  "fiftyTwoWeekLowChangePercent": 1.5349795,
  "fiftyTwoWeekRange": "1215.0 - 3385.0",
  "fiftyTwoWeekHighChange": -305.0,
  "fiftyTwoWeekHighChangePercent": -0.090103395,
  "fiftyTwoWeekChangePercent": 118.2849,
  "earningsTimestampStart": 1754548200,
  "earningsTimestampEnd": 1754893800,
  "isEarningsDateEstimate": true,
  "epsTrailingTwelveMonths": 349.58,
  "fiftyDayAverageChange": 32.95996,
  "fiftyDayAverageChangePercent": 0.010817043,
  "twoHundredDayAverageChange": 740.22,
  "twoHundredDayAverageChangePercent": 0.31636307,
  "sourceInterval": 15,
  "exchangeDataDelayedBy": 20,
  "corporateActions": [],
  "regularMarketTime": 1771569000,
  "exchange": "JPX",
  "messageBoardId": "finmb_267135698",
  "exchangeTimezoneName": "Asia/Tokyo",
  "exchangeTimezoneShortName": "JST",
  "gmtOffSetMilliseconds": 32400000,
  "market": "jp_market",
  "esgPopulated": false,
  "shortName": "HOKURYO CO LTD",
  "longName": "Hokuryo Co., Ltd.",
  "cryptoTradeable": false,
  "trailingPegRatio": null
}