{
  "address1": "1-50-12 Furuichicho",
  "city": "Maebashi",
  "zip": "371-8503",
  "country": "Japan",
  "phone": "81 2 7251 1617",
  "fax": "81 2 7290 1073",
  "website": "https://www.kanekoseeds.jp",
  "industry": "Agricultural Inputs",
  "industryKey": "agricultural-inputs",
  "industryDisp": "Agricultural Inputs",
  "sector": "Basic Materials",
  "sectorKey": "basic-materials",
  "sectorDisp": "Basic Materials",
  "longBusinessSummary": "Kaneko Seeds Co., Ltd., together with its subsidiaries, production and sale agricultural seeds in Japan. It operates through Seeds and Seedlings Business, Flower Business, Agricultural Materials Business, and Facility Materials Business segments. The company offers bulbs, and flower and horticultural supplies; vegetable and pasture seeds, virus-free seedlings, and seed potatoes; grass, forage crop, green manure crop, landscaping, and turfgrass seeds; and greenhouses and agricultural production materials. It also sells flower seedlings and vegetable seeds; young tomatoes and carnations; pesticides and coated fertilizers; and agricultural chemicals, resin materials, and hydroponic cultivation systems. In addition, the company engages in the sale and repair of greenhouse horticulture equipment; design, construct, and sale of hydroponic cultivation plants; and landscaping and slope construction contracting work. It serves home gardening enthusiasts and commercial growers; and home centers, gardening specialty stores, and gardening wholesalers. Kaneko Seeds Co., Ltd. was founded in 1895 and is headquartered in Maebashi, Japan.",
  "fullTimeEmployees": 695,
  "companyOfficers": [
    {
      "maxAge": 1,
      "name": "Mr. Masahiko  Kaneko",
      "age": 69,
      "title": "President & Representative Director",
      "yearBorn": 1956,
      "exercisedValue": 0,
      "unexercisedValue": 0
    },
    {
      "maxAge": 1,
      "name": "Mr. Hirokatsu  Hase",
      "age": 64,
      "title": "Senior MD & Director",
      "yearBorn": 1961,
      "exercisedValue": 0,
      "unexercisedValue": 0
    },
    {
      "maxAge": 1,
      "name": "Mr. Hiroshi  Hosoi",
      "age": 74,
      "title": "Senior MD & Head of Planning Promotion Office",
      "yearBorn": 1951,
      "exercisedValue": 0,
      "unexercisedValue": 0
    },
    {
      "maxAge": 1,
      "name": "Mr. Takeshi  Miyashita",
      "age": 61,
      "title": "MD & Director",
      "yearBorn": 1964,
      "exercisedValue": 0,
      "unexercisedValue": 0
    },
    {
      "maxAge": 1,
      "name": "Mr. Satoshi  Inoue",
      "age": 66,
      "title": "Manager of Vegetable Farming Department & Director",
      "yearBorn": 1959,
      "exercisedValue": 0,
      "unexercisedValue": 0
    },
    {
      "maxAge": 1,
      "name": "Mr. Kazuki  Ito",
      "age": 65,
      "title": "Senior MD & Director",
      "yearBorn": 1960,
      "exercisedValue": 0,
      "unexercisedValue": 0
    },
    {
      "maxAge": 1,
      "name": "Mr. Noboru  Nagai",
      "age": 69,
      "title": "Head of International Department",
      "yearBorn": 1956,
      "exercisedValue": 0,
      "unexercisedValue": 0
    },
    {
      "maxAge": 1,
      "name": "Mr. Hideaki  Hanzawa",
      "age": 63,
      "title": "Manager of Kunisada Plant Breeding Station & Director",
      "yearBorn": 1962,
      "exercisedValue": 0,
      "unexercisedValue": 0
    },
    {
      "maxAge": 1,
      "name": "Mr. Toshiki  Kanai",
      "age": 70,
      "title": "Head of System Marketing Department & Head of Development Department",
      "yearBorn": 1955,
      "exercisedValue": 0,
      "unexercisedValue": 0
    },
    {
      "maxAge": 1,
      "name": "Mr. Yoshiaki  Hayashi",
      "age": 67,
      "title": "Chief of Hashie Research Laboratory",
      "yearBorn": 1958,
      "exercisedValue": 0,
      "unexercisedValue": 0
    }
  ],
  "irWebsite": "http://www.kanekoseeds.jp/ir.html",
  "executiveTeam": [],
  "maxAge": 86400,
  "priceHint": 2,
  "previousClose": 1533.0,
  "open": 1533.0,
  "dayLow": 1510.0,
  "dayHigh": 1533.0,
  "regularMarketPreviousClose": 1533.0,
  "regularMarketOpen": 1533.0,
  "regularMarketDayLow": 1510.0,
  "regularMarketDayHigh": 1533.0,
  "dividendRate": 38.0,
  "dividendYield": 2.51,
  "exDividendDate": 1779926400,
  "payoutRatio": 0.32700002,
  "fiveYearAvgDividendYield": 2.12,
  "beta": 0.259,
  "trailingPE": 13.004214,
  "volume": 10600,
  "regularMarketVolume": 10600,
  "averageVolume": 17227,
  "averageVolume10days": 13440,
  "averageDailyVolume10Day": 13440,
  "bid": 1510.0,
  "ask": 1529.0,
  "bidSize": 0,
  "askSize": 0,
  "marketCap": 16580845568,
  "fiftyTwoWeekLow": 1310.0,
  "fiftyTwoWeekHigh": 1859.0,
  "allTimeHigh": 1868.0,
  "allTimeLow": 382.0,
  "priceToSalesTrailing12Months": 0.25411257,
  "fiftyDayAverage": 1547.48,
  "twoHundredDayAverage": 1497.315,
  "trailingAnnualDividendRate": 38.0,
  "trailingAnnualDividendYield": 0.024787998,
  "currency": "JPY",
  "tradeable": false,
  "enterpriseValue": 17095188480,
  "profitMargins": 0.01991,
  "floatShares": 8761221,
  "sharesOutstanding": 10966168,
  "heldPercentInsiders": 0.18823,
  "heldPercentInstitutions": 0.12023,
  "impliedSharesOutstanding": 10966168,
  "bookValue": 2295.783,
  "priceToBook": 0.65859884,
  "lastFiscalYearEnd": 1748649600,
  "nextFiscalYearEnd": 1780185600,
  "mostRecentQuarter": 1764460800,
  "earningsQuarterlyGrowth": -0.589,
  "netIncomeToCommon": 1299000064,
  "trailingEps": 116.27,
  "enterpriseToRevenue": 0.262,
  "enterpriseToEbitda": 7.863,
  "52WeekChange": 0.06855118,
  "SandP52WeekChange": 0.15480888,
  "lastDividendValue": 27.0,
  "lastDividendDate": 1779926400,
  "quoteType": "EQUITY",
  "currentPrice": 1512.0,
  "recommendationKey": "none",
  "totalCash": 2416000000,
  "totalCashPerShare": 220.313,
  "ebitda": 2174000128,
  "totalDebt": 2929999872,
  "quickRatio": 1.168,
  "currentRatio": 1.739,
  "totalRevenue": 65250000896,
  "debtToEquity": 11.638,
  "revenuePerShare": 5857.008,
  "returnOnAssets": 0.023610001,
  "returnOnEquity": 0.05234,
  "grossProfits": 9674999808,
  "freeCashflow": -904875008,
  "operatingCashflow": 2241999872,
  "earningsGrowth": -0.582,
  "revenueGrowth": 0.003,
  "grossMargins": 0.14828,
  "ebitdaMargins": 0.03332,
  "operatingMargins": 0.0072899996,
  "financialCurrency": "JPY",
  "symbol": "1376.T",
  "language": "en-US",
  "region": "US",
  "typeDisp": "Equity",
  "quoteSourceName": "Delayed Quote",
  "triggerable": false,
  "customPriceAlertConfidence": "LOW",
  "regularMarketChangePercent": -1.369863,
  "regularMarketPrice": 1512.0,
  "marketState": "CLOSED",
  "hasPrePostMarketData": false,
  "firstTradeDateMilliseconds": 947030400000,
  "regularMarketChange": -21.0,
  "regularMarketDayRange": "1510.0 - 1533.0",
  "fullExchangeName": "Tokyo",
  "averageDailyVolume3Month": 17227,
  "fiftyTwoWeekLowChange": 202.0,
  "fiftyTwoWeekLowChangePercent": 0.15419847,
  "fiftyTwoWeekRange": "1310.0 - 1859.0",
  "fiftyTwoWeekHighChange": -347.0,
  "fiftyTwoWeekHighChangePercent": -0.1866595,
  "fiftyTwoWeekChangePercent": 6.8551183,
  "earningsTimestampStart": 1751954400,
  "earningsTimestampEnd": 1752472800,
  "isEarningsDateEstimate": true,
  "epsTrailingTwelveMonths": 116.27,
  "fiftyDayAverageChange": -35.47998,
  "fiftyDayAverageChangePercent": -0.022927586,
  "twoHundredDayAverageChange": 14.685059,
  "twoHundredDayAverageChangePercent": 0.009807595,
  "sourceInterval": 15,
  "exchangeDataDelayedBy": 20,
  "corporateActions": [],
  "regularMarketTime": 1771569000,
  "exchange": "JPX",
  "messageBoardId": "finmb_4493094",
  "exchangeTimezoneName": "Asia/Tokyo",
  "exchangeTimezoneShortName": "JST",
  "gmtOffSetMilliseconds": 32400000,
  "market": "jp_market",
  "esgPopulated": false,
  "shortName": "KANEKO SEEDS CO",
  "longName": "Kaneko Seeds Co., Ltd.",
  "cryptoTradeable": false,
  "trailingPegRatio": null
}