{
  "address1": "Shibuya Cross Tower",
  "address2": "2-15-1, Shibuya Shibuya-ku",
  "city": "Tokyo",
  "zip": "150-0002",
  "country": "Japan",
  "phone": "81 3 3486 0606",
  "website": "https://www.softcreate-holdings.co.jp",
  "industry": "Information Technology Services",
  "industryKey": "information-technology-services",
  "industryDisp": "Information Technology Services",
  "sector": "Technology",
  "sectorKey": "technology",
  "sectorDisp": "Technology",
  "longBusinessSummary": "Softcreate Holdings Corp., through its subsidiaries, provides system integration and other IT-related services in Japan. It operates through the EC Solution Business and IT Solutions Business segments. The company offers EC solutions, comprising EC site design and construction, business consulting, promotion and marketing, and infrastructure services; IT outsourcing and cloud system integration services; and L2Blocker, a security product. It also provides workflow systems for small, medium, and large-scale firms. In addition, the company plans, produces, analyses, and operates content; and produces media and corporate sites. Further, it is involved in visual marketing-related businesses. Softcreate Holdings Corp. was incorporated in 1969 and is headquartered in Tokyo, Japan.",
  "fullTimeEmployees": 1101,
  "companyOfficers": [
    {
      "maxAge": 1,
      "name": "Mr. Masaru  Hayashi",
      "age": 80,
      "title": "Executive Chairman",
      "yearBorn": 1945,
      "fiscalYear": 2024,
      "totalPay": 258000,
      "exercisedValue": 0,
      "unexercisedValue": 0
    },
    {
      "maxAge": 1,
      "name": "Mr. Muneharu  Hayashi",
      "age": 51,
      "title": "President, CEO & Representative Director",
      "yearBorn": 1974,
      "fiscalYear": 2024,
      "exercisedValue": 0,
      "unexercisedValue": 0
    },
    {
      "maxAge": 1,
      "name": "Mr. Jun  Sato",
      "age": 51,
      "title": "Executive MD of Accounting and Finance Division & Director",
      "yearBorn": 1974,
      "fiscalYear": 2024,
      "exercisedValue": 0,
      "unexercisedValue": 0
    },
    {
      "maxAge": 1,
      "name": "Tomoo  Yoshikawa",
      "title": "Senior EO & Manager of Human Resources Development Department",
      "fiscalYear": 2024,
      "exercisedValue": 0,
      "unexercisedValue": 0
    },
    {
      "maxAge": 1,
      "name": "Mr. Masahiro  Nakagiri",
      "age": 62,
      "title": "Sr. Managing Executive Officer, Head of Business Management Division & Director",
      "yearBorn": 1963,
      "fiscalYear": 2024,
      "exercisedValue": 0,
      "unexercisedValue": 0
    },
    {
      "maxAge": 1,
      "name": "Mr. Masaya  Hayashi",
      "age": 48,
      "title": "Executive VP & Director",
      "yearBorn": 1977,
      "fiscalYear": 2024,
      "exercisedValue": 0,
      "unexercisedValue": 0
    },
    {
      "maxAge": 1,
      "name": "Hiroshi  Akiba",
      "title": "Managing Executive Officer and Manager of General & Personnel Affairs Department",
      "fiscalYear": 2024,
      "exercisedValue": 0,
      "unexercisedValue": 0
    },
    {
      "maxAge": 1,
      "name": "Kenichi  Shiraiwa",
      "title": "Managing Executive Officer",
      "fiscalYear": 2024,
      "exercisedValue": 0,
      "unexercisedValue": 0
    },
    {
      "maxAge": 1,
      "name": "Makoto  Ito",
      "title": "Executive Officer",
      "fiscalYear": 2024,
      "exercisedValue": 0,
      "unexercisedValue": 0
    },
    {
      "maxAge": 1,
      "name": "Fusao  Yamamoto",
      "title": "Executive Officer",
      "fiscalYear": 2024,
      "exercisedValue": 0,
      "unexercisedValue": 0
    }
  ],
  "compensationAsOfEpochDate": 1735603200,
  "executiveTeam": [],
  "maxAge": 86400,
  "priceHint": 2,
  "previousClose": 1984.0,
  "open": 1978.0,
  "dayLow": 1975.0,
  "dayHigh": 2031.0,
  "regularMarketPreviousClose": 1984.0,
  "regularMarketOpen": 1978.0,
  "regularMarketDayLow": 1975.0,
  "regularMarketDayHigh": 2031.0,
  "dividendRate": 62.0,
  "dividendYield": 3.13,
  "exDividendDate": 1774828800,
  "payoutRatio": 0.4047,
  "fiveYearAvgDividendYield": 1.8,
  "beta": 0.434,
  "trailingPE": 14.001245,
  "volume": 53300,
  "regularMarketVolume": 53300,
  "averageVolume": 36320,
  "averageVolume10days": 65150,
  "averageDailyVolume10Day": 65150,
  "bid": 2015.0,
  "ask": 2030.0,
  "bidSize": 0,
  "askSize": 0,
  "marketCap": 50546003968,
  "fiftyTwoWeekLow": 1674.0,
  "fiftyTwoWeekHigh": 2425.0,
  "allTimeHigh": 2545.0,
  "allTimeLow": 91.666664,
  "priceToSalesTrailing12Months": 1.5111619,
  "fiftyDayAverage": 2105.92,
  "twoHundredDayAverage": 2161.285,
  "trailingAnnualDividendRate": 58.5,
  "trailingAnnualDividendYield": 0.029485887,
  "currency": "JPY",
  "tradeable": false,
  "enterpriseValue": 37506465792,
  "profitMargins": 0.117410004,
  "floatShares": 12372839,
  "sharesOutstanding": 24960990,
  "heldPercentInsiders": 0.4427,
  "heldPercentInstitutions": 0.107370004,
  "impliedSharesOutstanding": 24960990,
  "bookValue": 955.633,
  "priceToBook": 2.1190143,
  "lastFiscalYearEnd": 1743379200,
  "nextFiscalYearEnd": 1774915200,
  "mostRecentQuarter": 1767139200,
  "netIncomeToCommon": 3927276032,
  "trailingEps": 144.63,
  "lastSplitFactor": "2:1",
  "lastSplitDate": 1680134400,
  "enterpriseToRevenue": 1.121,
  "52WeekChange": -0.03736049,
  "SandP52WeekChange": 0.11527538,
  "lastDividendValue": 31.0,
  "lastDividendDate": 1774828800,
  "quoteType": "EQUITY",
  "currentPrice": 2025.0,
  "recommendationKey": "none",
  "totalCash": 16620085248,
  "totalCashPerShare": 663.858,
  "totalDebt": 0,
  "quickRatio": 2.749,
  "currentRatio": 3.024,
  "totalRevenue": 33448435712,
  "revenuePerShare": 1341.744,
  "returnOnAssets": 0.10658,
  "returnOnEquity": 0.17249,
  "grossProfits": 13830886400,
  "grossMargins": 0.41349998,
  "ebitdaMargins": 0.0,
  "operatingMargins": 0.21103,
  "financialCurrency": "JPY",
  "symbol": "3371.T",
  "language": "en-US",
  "region": "US",
  "typeDisp": "Equity",
  "quoteSourceName": "Delayed Quote",
  "triggerable": false,
  "customPriceAlertConfidence": "LOW",
  "regularMarketChange": 41.0,
  "regularMarketDayRange": "1975.0 - 2031.0",
  "fullExchangeName": "Tokyo",
  "averageDailyVolume3Month": 36320,
  "fiftyTwoWeekLowChange": 351.0,
  "fiftyTwoWeekLowChangePercent": 0.20967741,
  "fiftyTwoWeekRange": "1674.0 - 2425.0",
  "fiftyTwoWeekHighChange": -400.0,
  "fiftyTwoWeekHighChangePercent": -0.16494845,
  "fiftyTwoWeekChangePercent": -3.736049,
  "earningsTimestampStart": 1753855200,
  "earningsTimestampEnd": 1754287200,
  "isEarningsDateEstimate": true,
  "epsTrailingTwelveMonths": 144.63,
  "fiftyDayAverageChange": -80.91992,
  "fiftyDayAverageChangePercent": -0.038424976,
  "twoHundredDayAverageChange": -136.28491,
  "twoHundredDayAverageChangePercent": -0.063057356,
  "sourceInterval": 15,
  "exchangeDataDelayedBy": 20,
  "shortName": "SOFTCREATE HOLDINGS CORP",
  "longName": "Softcreate Holdings Corp.",
  "marketState": "PREPRE",
  "hasPrePostMarketData": false,
  "firstTradeDateMilliseconds": 1220572800000,
  "corporateActions": [],
  "regularMarketTime": 1771309800,
  "exchange": "JPX",
  "messageBoardId": "finmb_21860290",
  "exchangeTimezoneName": "Asia/Tokyo",
  "exchangeTimezoneShortName": "JST",
  "gmtOffSetMilliseconds": 32400000,
  "market": "jp_market",
  "esgPopulated": false,
  "cryptoTradeable": false,
  "regularMarketChangePercent": 2.0665324,
  "regularMarketPrice": 2025.0,
  "trailingPegRatio": null
}