{
  "address1": "8-537-1, Doki-cho-higashi",
  "city": "Marugame",
  "zip": "763-8504",
  "country": "Japan",
  "phone": "81 8 7722 4111",
  "website": "https://www.shikoku.co.jp",
  "industry": "Specialty Chemicals",
  "industryKey": "specialty-chemicals",
  "industryDisp": "Specialty Chemicals",
  "sector": "Basic Materials",
  "sectorKey": "basic-materials",
  "sectorDisp": "Basic Materials",
  "longBusinessSummary": "Shikoku Kasei Holdings Corporation engages in the research and development, manufacture, and sale of chemical products and housing materials in Japan and internationally. It offers carbon disulfide and hydrogen sulfide, sodium sulfate and carbonate, insoluble sulfur, and chlorinated isocyanurates; organic solderability preservative; chemical adhesion process; microetching solution; imidazole type and adduct type latent curing agents; adhesion and heat resistance improver; isocyanuric acid derivatives; glycoluril derivatives; cationic curing materials; and THEIC materials. The company provides automatic chlorine feeders, bacteria enzymes, and urinary calculus removers; and industrial chemicals, pharmaceuticals, quasi-drugs, fertilizers, and agricultural chemicals. In addition, it offers housing materials comprising interior finishing and paving materials, and residential and landscape exterior products. Further, the company is involved in the design, production, development, and installation of shutters and other retail outlet fixtures, as well as provides technical services; development and sale of computer software; management of computer systems; operation of the Mosburger chain of hamburger shops; sale of giftware and daily use products; design, installation, and maintenance management of water treatment for sewage and septic tanks; construction of drainage pipe connection; inspection and cleaning of water storage tanks; collection and transportation of general and industrial waste materials; provision of information services; damage-insurance and life-insurance agency; packaging and transportation; and housing renovation and solar photovoltaic generation activities. Additionally, it offers environmental measurement authentication, and quality testing of drinking water services; construction materials; and design and construction of related facilities. The company was incorporated in 1947 and is headquartered in Marugame, Japan.",
  "companyOfficers": [
    {
      "maxAge": 1,
      "name": "Mr. Mitsunori  Watanabe",
      "age": 68,
      "title": "President, CEO, Group Compliance Officer & Representative Director",
      "yearBorn": 1957,
      "exercisedValue": 0,
      "unexercisedValue": 0
    },
    {
      "maxAge": 1,
      "name": "Mr. Makoto  Hamazaki",
      "age": 67,
      "title": "MD & Director",
      "yearBorn": 1958,
      "exercisedValue": 0,
      "unexercisedValue": 0
    },
    {
      "maxAge": 1,
      "name": "Mr. Yoshinori  Manabe",
      "age": 61,
      "title": "MD & Director",
      "yearBorn": 1964,
      "exercisedValue": 0,
      "unexercisedValue": 0
    }
  ],
  "irWebsite": "http://www.shikoku.co.jp/eng/ir/stocks.html",
  "executiveTeam": [],
  "maxAge": 86400,
  "priceHint": 2,
  "previousClose": 4715.0,
  "open": 4725.0,
  "dayLow": 4660.0,
  "dayHigh": 4830.0,
  "regularMarketPreviousClose": 4715.0,
  "regularMarketOpen": 4725.0,
  "regularMarketDayLow": 4660.0,
  "regularMarketDayHigh": 4830.0,
  "dividendRate": 60.0,
  "dividendYield": 1.27,
  "exDividendDate": 1782691200,
  "payoutRatio": 0.2848,
  "fiveYearAvgDividendYield": 1.98,
  "beta": 0.31,
  "trailingPE": 24.751705,
  "forwardPE": 25.384615,
  "volume": 242700,
  "regularMarketVolume": 242700,
  "averageVolume": 139628,
  "averageVolume10days": 231900,
  "averageDailyVolume10Day": 231900,
  "bid": 4785.0,
  "ask": 4805.0,
  "bidSize": 0,
  "askSize": 0,
  "marketCap": 206948040704,
  "fiftyTwoWeekLow": 1519.0,
  "fiftyTwoWeekHigh": 4830.0,
  "allTimeHigh": 4795.0,
  "allTimeLow": 258.0,
  "priceToSalesTrailing12Months": 2.9269226,
  "fiftyDayAverage": 3200.3,
  "twoHundredDayAverage": 2461.555,
  "trailingAnnualDividendRate": 0.0,
  "trailingAnnualDividendYield": 0.0,
  "currency": "JPY",
  "tradeable": false,
  "enterpriseValue": 185005408256,
  "profitMargins": 0.11964,
  "floatShares": 24572435,
  "sharesOutstanding": 43249326,
  "heldPercentInsiders": 0.30066,
  "heldPercentInstitutions": 0.26408002,
  "impliedSharesOutstanding": 43249326,
  "bookValue": 2165.904,
  "priceToBook": 2.2092392,
  "lastFiscalYearEnd": 1767139200,
  "nextFiscalYearEnd": 1798675200,
  "mostRecentQuarter": 1767139200,
  "earningsQuarterlyGrowth": 0.189,
  "netIncomeToCommon": 8458999808,
  "trailingEps": 193.32,
  "forwardEps": 188.5,
  "enterpriseToRevenue": 2.617,
  "enterpriseToEbitda": 12.84,
  "52WeekChange": 1.3681567,
  "SandP52WeekChange": 0.11527538,
  "lastDividendValue": 30.0,
  "lastDividendDate": 1798502400,
  "quoteType": "EQUITY",
  "currentPrice": 4785.0,
  "targetHighPrice": 3200.0,
  "targetLowPrice": 3200.0,
  "targetMeanPrice": 3200.0,
  "targetMedianPrice": 3200.0,
  "recommendationKey": "none",
  "numberOfAnalystOpinions": 1,
  "totalCash": 47429001216,
  "totalCashPerShare": 1095.237,
  "ebitda": 14408999936,
  "totalDebt": 24416999424,
  "quickRatio": 2.342,
  "currentRatio": 2.913,
  "totalRevenue": 70704996352,
  "debtToEquity": 25.811,
  "revenuePerShare": 1614.091,
  "returnOnAssets": 0.04849,
  "returnOnEquity": 0.09482,
  "grossProfits": 30651000832,
  "freeCashflow": 2204124928,
  "operatingCashflow": 10981000192,
  "earningsGrowth": 0.231,
  "revenueGrowth": 0.105,
  "grossMargins": 0.43351,
  "ebitdaMargins": 0.20379,
  "operatingMargins": 0.14228,
  "financialCurrency": "JPY",
  "symbol": "4099.T",
  "language": "en-US",
  "region": "US",
  "typeDisp": "Equity",
  "quoteSourceName": "Delayed Quote",
  "triggerable": false,
  "customPriceAlertConfidence": "LOW",
  "cryptoTradeable": false,
  "hasPrePostMarketData": false,
  "firstTradeDateMilliseconds": 978307200000,
  "regularMarketChange": 70.0,
  "regularMarketDayRange": "4660.0 - 4830.0",
  "fullExchangeName": "Tokyo",
  "averageDailyVolume3Month": 139628,
  "fiftyTwoWeekLowChange": 3266.0,
  "fiftyTwoWeekLowChangePercent": 2.1500988,
  "fiftyTwoWeekRange": "1519.0 - 4830.0",
  "fiftyTwoWeekHighChange": -45.0,
  "fiftyTwoWeekHighChangePercent": -0.00931677,
  "fiftyTwoWeekChangePercent": 136.81567,
  "earningsTimestampStart": 1753671600,
  "earningsTimestampEnd": 1754017200,
  "isEarningsDateEstimate": true,
  "epsTrailingTwelveMonths": 193.32,
  "epsForward": 188.5,
  "fiftyDayAverageChange": 1584.7,
  "fiftyDayAverageChangePercent": 0.4951723,
  "twoHundredDayAverageChange": 2323.445,
  "twoHundredDayAverageChangePercent": 0.94389325,
  "sourceInterval": 15,
  "exchangeDataDelayedBy": 20,
  "prevName": "Shikoku Chemicals Corporation",
  "nameChangeDate": "2026-02-17",
  "marketState": "PREPRE",
  "corporateActions": [],
  "regularMarketTime": 1771309800,
  "exchange": "JPX",
  "messageBoardId": "finmb_876336",
  "exchangeTimezoneName": "Asia/Tokyo",
  "exchangeTimezoneShortName": "JST",
  "gmtOffSetMilliseconds": 32400000,
  "market": "jp_market",
  "esgPopulated": false,
  "regularMarketChangePercent": 1.4846236,
  "regularMarketPrice": 4785.0,
  "shortName": "SHIKOKU KASEI HOLDINGS CORPORAT",
  "longName": "Shikoku Kasei Holdings Corporation",
  "trailingPegRatio": null
}