{
  "address1": "Shin Aoyama Building East",
  "address2": "13th and 17th Floor 1-1, Minamiaoyama 1-Chome Minato-ku",
  "city": "Tokyo",
  "zip": "107-0062",
  "country": "Japan",
  "phone": "81 3 5411 3411",
  "fax": "81 3 5411 1524",
  "website": "https://www.seiren.com",
  "industry": "Textile Manufacturing",
  "industryKey": "textile-manufacturing",
  "industryDisp": "Textile Manufacturing",
  "sector": "Consumer Cyclical",
  "sectorKey": "consumer-cyclical",
  "sectorDisp": "Consumer Cyclical",
  "longBusinessSummary": "Seiren Co.,Ltd. manufactures and markets textile products, industrial machines, and electronic parts in Japan and internationally. The company operates through five segments: Automotive Upholstery Materials, High Fashion Materials, Electronics Materials, Environmental & Life Materials, and Medical Materials. The Automotive Upholstery Materials segment offers materials for interiors of automobiles, railway rolling stock, etc., as well as seat covers, air bags, and decorative parts. The High Fashion Materials segment engages in the apparel textile processing; and provides apparel products. The Electronics Materials segment offers conductive materials, industrial wiping cloths, Viscotecs systems and supply, electronic devices, silicon wafer film deposition, and artificial satellites. The Environmental & Life Materials provides construction materials, interior materials, health/nursing products, and environmental/civil engineering materials. The Medical Materials offers medical materials, cosmetics, and water processing materials. It provides digital production systems; and civil engineering, construction, and industrial materials. The company also offers eco-friendly materials; beauty/health care materials; medical/nursing acre materials; and life/interior materials. In addition, it engages in the automotive interior, clothing materials, and textile finishing materials businesses. The company was formerly known as Fukui Seiren Kako Co., Ltd. and changed its name to Seiren Co.,Ltd. in 1973. Seiren Co.,Ltd. was founded in 1889 and is headquartered in Tokyo, Japan.",
  "fullTimeEmployees": 6228,
  "companyOfficers": [
    {
      "maxAge": 1,
      "name": "Mr. Tatsuo  Kawada",
      "age": 85,
      "title": "Chairman of the Board & CEO",
      "yearBorn": 1940,
      "fiscalYear": 2025,
      "totalPay": 162000000,
      "exercisedValue": 0,
      "unexercisedValue": 0
    },
    {
      "maxAge": 1,
      "name": "Mr. Yu  Hui",
      "age": 62,
      "title": "Executive Officer & Vice Chairman",
      "yearBorn": 1963,
      "fiscalYear": 2025,
      "totalPay": 70000000,
      "exercisedValue": 0,
      "unexercisedValue": 0
    },
    {
      "maxAge": 1,
      "name": "Mr. Hideyuki  Yamada",
      "age": 64,
      "title": "President, COO & CTO & Representative Director",
      "yearBorn": 1961,
      "fiscalYear": 2025,
      "totalPay": 111000000,
      "exercisedValue": 0,
      "unexercisedValue": 0
    },
    {
      "maxAge": 1,
      "name": "Mr. Tomofumi  Katsuki",
      "age": 63,
      "title": "Sr. Managing Exec. Officer, Head of Admin Div., GM of Global Business Audit Office & Director",
      "yearBorn": 1962,
      "fiscalYear": 2025,
      "exercisedValue": 0,
      "unexercisedValue": 0
    },
    {
      "maxAge": 1,
      "name": "Mr. Koji  Kawada",
      "age": 54,
      "title": "Executive VP, Chief Strategy Officer, CMO, Sales Manager & Representative Director",
      "yearBorn": 1971,
      "fiscalYear": 2025,
      "exercisedValue": 0,
      "unexercisedValue": 0
    },
    {
      "maxAge": 1,
      "name": "Masaki  Teramae",
      "age": 69,
      "title": "Managing Executive Officer",
      "yearBorn": 1956,
      "fiscalYear": 2025,
      "exercisedValue": 0,
      "unexercisedValue": 0
    },
    {
      "maxAge": 1,
      "name": "Yasunori  Takezawa",
      "age": 60,
      "title": "Managing Executive Officer & Head of North American Business",
      "yearBorn": 1965,
      "fiscalYear": 2025,
      "exercisedValue": 0,
      "unexercisedValue": 0
    },
    {
      "maxAge": 1,
      "name": "Hiroshi  Kimura",
      "title": "Senior Executive Officer",
      "fiscalYear": 2025,
      "exercisedValue": 0,
      "unexercisedValue": 0
    },
    {
      "maxAge": 1,
      "name": "Tsuneharu  Saito",
      "title": "Head of Global Airbag Bus, GM of Airbag Business Div., Airbag Sales Dept. & GM of Production Section",
      "fiscalYear": 2025,
      "exercisedValue": 0,
      "unexercisedValue": 0
    },
    {
      "maxAge": 1,
      "name": "Tomohiro  Izumi",
      "title": "Managing Executive Officer",
      "fiscalYear": 2025,
      "exercisedValue": 0,
      "unexercisedValue": 0
    }
  ],
  "auditRisk": 4,
  "boardRisk": 7,
  "compensationRisk": 1,
  "shareHolderRightsRisk": 3,
  "overallRisk": 6,
  "governanceEpochDate": 1769904000,
  "compensationAsOfEpochDate": 1767139200,
  "irWebsite": "http://www.seiren.com/english/invest/",
  "executiveTeam": [],
  "maxAge": 86400,
  "priceHint": 2,
  "previousClose": 3435.0,
  "open": 3455.0,
  "dayLow": 3420.0,
  "dayHigh": 3520.0,
  "regularMarketPreviousClose": 3435.0,
  "regularMarketOpen": 3455.0,
  "regularMarketDayLow": 3420.0,
  "regularMarketDayHigh": 3520.0,
  "dividendRate": 76.0,
  "dividendYield": 2.21,
  "exDividendDate": 1774828800,
  "payoutRatio": 0.2974,
  "fiveYearAvgDividendYield": 2.03,
  "beta": 0.538,
  "trailingPE": 13.63672,
  "forwardPE": 13.283781,
  "volume": 219300,
  "regularMarketVolume": 219300,
  "averageVolume": 157879,
  "averageVolume10days": 208560,
  "averageDailyVolume10Day": 208560,
  "bid": 3480.0,
  "ask": 3490.0,
  "bidSize": 0,
  "askSize": 0,
  "marketCap": 204385026048,
  "fiftyTwoWeekLow": 2001.0,
  "fiftyTwoWeekHigh": 3520.0,
  "allTimeHigh": 3480.0,
  "allTimeLow": 252.0,
  "priceToSalesTrailing12Months": 1.2418281,
  "fiftyDayAverage": 3176.5,
  "twoHundredDayAverage": 2855.575,
  "trailingAnnualDividendRate": 76.0,
  "trailingAnnualDividendYield": 0.022125183,
  "currency": "JPY",
  "tradeable": false,
  "enterpriseValue": 176261218304,
  "profitMargins": 0.095769994,
  "floatShares": 46491681,
  "sharesOutstanding": 58647069,
  "heldPercentInsiders": 0.11668,
  "heldPercentInstitutions": 0.40293,
  "impliedSharesOutstanding": 58647069,
  "bookValue": 2591.34,
  "priceToBook": 1.344864,
  "lastFiscalYearEnd": 1743379200,
  "nextFiscalYearEnd": 1774915200,
  "mostRecentQuarter": 1767139200,
  "earningsQuarterlyGrowth": 0.154,
  "netIncomeToCommon": 15763000320,
  "trailingEps": 255.56,
  "forwardEps": 262.35,
  "enterpriseToRevenue": 1.071,
  "enterpriseToEbitda": 6.674,
  "52WeekChange": 0.26846385,
  "SandP52WeekChange": 0.11527538,
  "lastDividendValue": 38.0,
  "lastDividendDate": 1774828800,
  "quoteType": "EQUITY",
  "currentPrice": 3485.0,
  "targetHighPrice": 4450.0,
  "targetLowPrice": 3200.0,
  "targetMeanPrice": 3825.0,
  "targetMedianPrice": 3825.0,
  "recommendationKey": "none",
  "numberOfAnalystOpinions": 2,
  "totalCash": 38050000896,
  "totalCashPerShare": 647.023,
  "ebitda": 26409000960,
  "totalDebt": 8599000064,
  "quickRatio": 2.306,
  "currentRatio": 3.493,
  "totalRevenue": 164583997440,
  "debtToEquity": 5.625,
  "revenuePerShare": 2804.869,
  "returnOnAssets": 0.06388,
  "returnOnEquity": 0.109160006,
  "grossProfits": 45731000320,
  "operatingCashflow": 18769999872,
  "earningsGrowth": 0.175,
  "revenueGrowth": 0.049,
  "grossMargins": 0.27786,
  "ebitdaMargins": 0.16046,
  "operatingMargins": 0.13495,
  "financialCurrency": "JPY",
  "symbol": "3569.T",
  "language": "en-US",
  "region": "US",
  "typeDisp": "Equity",
  "quoteSourceName": "Delayed Quote",
  "triggerable": false,
  "customPriceAlertConfidence": "LOW",
  "longName": "Seiren Co.,Ltd.",
  "marketState": "PREPRE",
  "shortName": "SEIREN CO LTD",
  "regularMarketChange": 50.0,
  "regularMarketDayRange": "3420.0 - 3520.0",
  "fullExchangeName": "Tokyo",
  "averageDailyVolume3Month": 157879,
  "fiftyTwoWeekLowChange": 1484.0,
  "fiftyTwoWeekLowChangePercent": 0.7416292,
  "fiftyTwoWeekRange": "2001.0 - 3520.0",
  "fiftyTwoWeekHighChange": -35.0,
  "fiftyTwoWeekHighChangePercent": -0.009943182,
  "fiftyTwoWeekChangePercent": 26.846386,
  "earningsTimestampStart": 1754460000,
  "earningsTimestampEnd": 1754978400,
  "isEarningsDateEstimate": true,
  "epsTrailingTwelveMonths": 255.56,
  "epsForward": 262.35,
  "fiftyDayAverageChange": 308.5,
  "fiftyDayAverageChangePercent": 0.09711947,
  "twoHundredDayAverageChange": 629.42505,
  "twoHundredDayAverageChangePercent": 0.22041972,
  "sourceInterval": 15,
  "exchangeDataDelayedBy": 20,
  "cryptoTradeable": false,
  "hasPrePostMarketData": false,
  "firstTradeDateMilliseconds": 978566400000,
  "corporateActions": [],
  "regularMarketTime": 1771309800,
  "exchange": "JPX",
  "messageBoardId": "finmb_880837",
  "exchangeTimezoneName": "Asia/Tokyo",
  "exchangeTimezoneShortName": "JST",
  "gmtOffSetMilliseconds": 32400000,
  "market": "jp_market",
  "esgPopulated": false,
  "regularMarketChangePercent": 1.4556041,
  "regularMarketPrice": 3485.0,
  "trailingPegRatio": null
}